jsin/__init__.py
jsin/exceptions.py
jsin/infer.py
jsin/inferer.py
jsin/pydanticalize.py
jsin/schematic_tree_nodes.py
jsin/signature.py
jsin-0.0.5.dist-info/METADATA
jsin-0.0.5.dist-info/WHEEL
jsin-0.0.5.dist-info/licenses/LICENSE
jsin-0.0.5.dist-info/RECORD
