Metadata-Version: 2.4
Name: jsin
Version: 0.0.5
Summary: JSON schema inferer
Project-URL: Homepage, https://github.com/mumingpo/jsin
Project-URL: Issues, https://github.com/mumingpo/jsin/issues
Author-email: mumingpo <mumingpo@gmail.com>
License-Expression: MIT
License-File: LICENSE
Classifier: Operating System :: OS Independent
Classifier: Programming Language :: Python :: 3
Requires-Python: >=3.9
